Fusion-Core-Base/decode_32.v
/*
*
*  This file is part of Fusion-Core-ISA.
*  Author: Dylan Wadler dylan@fusion-core.org
*
*  Fusion-Core-ISA is free software: you can redistribute it and/or modify
*  it under the terms of the GNU General Public License as published by
*  the Free Software Foundation, either version 3 of the License, or
*  (at your option) any later version.
*
*  Fusion-Core-ISA is distributed in the hope that it will be useful,
*  but WITHOUT ANY WARRANTY; without even the implied warranty of
*  MERCHANTABILITY or FITNESS FOR A PARTICULAR PURPOSE.  See the
*  GNU General Public License for more details.
*
*  You should have received a copy of the GNU General Public License
*  along with Fusion-Core-ISA.  If not, see <http://www.gnu.org/licenses/>.
*/

/*** Defines  ***/
/*System because it's special*/
`define	OPC_SYS		 5'b110000;

module decode_32(
	input[31:0] 	insn_in,			//input instruction
	input			reset_in,			//input reset line
	input			clk_in,				//input clock
	input[31:0]		insn_pc_in,			//input program counter address
	input			stall_in,			//input stall signal


	/*Operand output connections*/
	output reg	[4:0] 	reg_select_out,		//output register bank select
	output reg 	[4:0]	rsa_out,			//output of register a address
	output reg	[4:0] 	rsb_out,			//output of register b address
	output reg	[4:0] 	rd_out, 			//output of destination register address
	output reg	[20:0] 	imm_out,			//output of immediate value
											//using largest immediate value
											//size

	/*Control Signals*/
	output 	reg [3:0] aluop_out,
	output	reg jlnk_out,
	output	reg pc_change_rel_out,
	output	reg pc_change_abs_out,
	output	reg mem_read_out,
	output	reg mem_write_out,

	/*Flag outputs*/
	output	reg nri_flg_out,		//output of 'not real instruction' flag
	output	reg [1:0] branch_funct_out,	//branch function; taken from the funct field
	output	reg stall_out,

	/*System instruction signals*/
	output		reg 		memsync_out,
	output		reg 		syscall_out,
	output		reg 		pem_inc_req_out,
	output		reg 		pem_dec_req_out,
	output		reg [7:0]	sysreg_addr_out,	//for reading and writing to system registers
	output		reg [7:0]	sysreg_data_out,
	input 			[7:0]	sysreg_data_in,


	/* Misc. Outputs*/
	output	reg [31:0] insn_pc_out,
	/*Co-processor connections*/
	output	reg [30:0] cp_insn_out

	);

	/* Pipeline information */
	localparam PIPELINE_LENGTH 	= 5; 
	localparam PIPELINEL_2		= $clog2(PIPELINE_LENGTH);
	/*Defining opcodes to make things easier*/
	localparam OPC_INT 	 	= 5'b010011;
	localparam OPC_IMM 		= 5'b010110;
	localparam OPC_LI		= 5'b010000;
	localparam OPC_BRANCH	= 5'b001101;
	localparam OPC_JMP		= 5'b001100;
	localparam OPC_JLNK		= 5'b000100;
	localparam OPC_LD		= 5'b011110;
	localparam OPC_ST		= 5'b011101;

	/*Wire connections*/
	wire[5:0] 	opcode_w;
	wire[4:0] 	rsa_addr_w;
	wire[4:0] 	rsb_addr_w;
	wire[4:0] 	rd_addr_w;
	wire[3:0] 	aluop_w;

	/*Funct Variants*/
	wire[1:0]	funct_ld_w;
	wire[1:0]	funct_st_w;
	wire[3:0]	dsel_li_w;
	wire[1:0]	funct_b_w;
	wire[7:0]	funct_sys_w;

	/*Immediate Variants*/
	wire[11:0]	imm_i_w;
	wire[13:0]	imm_ld_w;
	wire[15:0]	imm_li_w;
	wire[13:0]	imm_st_w;
	wire[20:0]	imm_j_w;
	wire[13:0]	imm_b_w;
	wire[7:0]	imm_sys_w;

	/*OPCode generated signals*/

	/*Resouce usage*/
	wire		use_alu_w;
	wire		is_cp_insn_w;			//is coprocessor instruction
	wire		pc_change_w;			//instruction can change the pc
	wire		mem_access_w;
	wire		pc_link_w;				//jump that requires linking to ra
	wire		sys_insn_w;

	/*secondary calculated resource usage*/
	wire		mem_read_req_w;
	wire		mem_write_req_w;
	wire		pc_abs_w;
	wire		pc_rel_w;
	wire		memsync_w;
	
	/*ALU op signal selection*/
	wire		aluop_intsig_w; // integer/register operation field used
	wire		aluop_addsig_w; // fixed add operation
	wire		aluop_bsig_w;   // branch operation decode value

	/*Operand usage*/
	wire		use_rd_w;
	wire		use_rsa_w;
	wire		use_rsb_w;
	wire		use_imm_w;
	wire [4:0]	imm_sel_w;


	/*Assignments*/
	assign 	opcode_w 		= insn_in[31:26];
	assign 	rsa_addr_w 		= insn_in[20:16];
	assign 	rsb_addr_w 		= insn_in[15:11]; 
	assign 	rd_addr_w		= insn_in[25:21];
	assign 	aluop_w  		= insn_in[3:0];

 	assign	funct_ld_w 		= insn_in[15:14];
	assign	funct_st_w		= insn_in[25:24];
	assign	dsel_li_w		= insn_in[20:16];
	assign	funct_b_w		= insn_in[1:0];
	assign	funct_sys_w		= insn_in[15:8];

	assign	imm_i_w 		= insn_in[15:4];
	assign	imm_ld_w		= insn_in[13:0];
	assign	imm_li_w		= insn_in[15:0];
	assign	imm_st_w		= {insn_in[13:11],insn_in[10:0]};
	assign	imm_j_w			= {insn_in[25:21],insn_in[15:0]};
	assign	imm_b_w			= {insn_in[25:21],insn_in[10:2]};
	assign	imm_sys_w		= insn_in[7:0];   
	assign  imm_sel_w		= (use_imm_w) ?opcode_w[4:0] : 5'b0; //if using immediate, need to determine output

	assign 	is_cp_insn_w	= opcode_w[5];
	assign	pc_change_w		= ~opcode_w[4];				
	assign	mem_access_w	= opcode_w[4] & opcode_w[3];
	assign	pc_link_w		= ~(opcode_w[4] | opcode_w[3]);				
	assign	sys_insn_w		= is_cp_insn_w & opcode_w[4];
	assign 	memsync_w = (sys_insn_w && ( (funct_sys_w & 8'h04) || (funct_sys_w & 8'b0 ) )); //if sync or syscall, need to sync memory 

	assign	use_rd_w		= (opcode_w[1] | opcode_w[0]) & (~opcode_w[2] | opcode_w[1]);
	assign	use_rsa_w		= (opcode_w[2] | opcode_w[1]);
	assign	use_rsb_w		= (opcode_w[2] & opcode_w[0]) | ( opcode_w[1] & opcode_w[0] );
	assign	use_imm_w 		= (opcode_w[2] | ~opcode_w[1]);

    assign 	aluop_intsig_w	= (opcode_w[4] & opcode_w[1]) & ~(opcode_w[5] & opcode_w[3]) & (opcode_w[2] ^ opcode_w[0]); //used for imm and int
    assign	aluop_addsig_w	= pc_rel_w;//used for jump (relative)
    assign	aluop_bsig_w	= (pc_change_w) & (use_rsb_w); //is a branch 

	/*Memory read/write signal creation*/

	/*use_rsb has simpler gate usage, which is better than using use_rd for
	* determining read or writes */
	assign 	mem_write_req_w = (mem_access_w & use_rsb_w); //store instructions use rsb, not rd
	assign 	mem_read_req_w	= (mem_access_w & ~use_rsb_w); //load instructions use rd, not rsb
	
	/* opcode_w[2] & ~opcode_w[1] denotes */ 

//	assign  pc_rel_w		= (pc_change_w & 	( (opcode_w[2:0] && 3'b101)  || (rsa_addr_w == (5'b0)) ) ); //not jr/jrl or branch
	assign  pc_rel_w		= (pc_change_w &	( (opcode_w[0]) || (opcode_w[2] & (rsa_addr_w == (5'b0))))); //so nops don't cause pc changes
	assign	pc_abs_w		= (pc_change_w &   ~( (opcode_w[2:0] && 3'b101)  || (rsa_addr_w == (5'b0)) ) );

/* Internal registers*/
	reg	[PIPELINEL_2 - 1 : 0]	memstall_count; //counter for stalls in pipeline


/*** LOGIC SECTION ****/

always@(~reset_in or stall_in) begin //while in reset or stalling

	reg_select_out 		<= 5'b0;			//output register bank select
	rsa_out 			<= 5'b0;			//output of register a address
	rsb_out 			<= 5'b0;			//output of register b address
	rd_out				<= 5'b0; 			//output of destination register address
	imm_out				<= 21'b0;			//output of immediate value
	  									//using largest immediate value
	  									//size

	aluop_out			<= 4'b0;
	jlnk_out			<= 1'b0;
	pc_change_rel_out	<= 1'b0;
	pc_change_abs_out	<= 1'b0;
	mem_read_out		<= 1'b0;
	mem_write_out		<= 1'b0;

	nri_flg_out			<= 1'b0;		//output of 'not real instruction' flag
	branch_funct_out	<= 2'b0;	//branch function; taken from the funct field

	memsync_out			<= 1'b0;
	syscall_out			<= 1'b0;
	pem_inc_req_out		<= 1'b0;
	pem_dec_req_out		<= 1'b0;
	sysreg_addr_out		<= 8'b0;
	sysreg_data_out		<= 8'b0;

	insn_pc_out			<= 32'h0; 
	cp_insn_out			<= 32'h0;
	stall_out			<= 1'b0;

end


always@(posedge clk_in, reset_in, ~stall_in) begin //make sure that reset has to be high for this to work
	/*** Determining ALUOP value ***/
	if (aluop_intsig_w) begin //uses ALUOP field
		aluop_out = aluop_w;
	end else if (aluop_addsig_w) begin //just add, so jumps
		aluop_out = 4'b0000;
	end else if (aluop_bsig_w) begin //branches, so need to decode the funct field
		aluop_out = 4'b1100; //like compare insn, but does different things
	end else begin
		aluop_out = 4'b1111; //unused code, use as nop? need to define in documentation
	end

	/*Branch funct assignment*/
	branch_funct_out = (aluop_bsig_w) ? (funct_b_w) : (2'b0);

	/*Co-processor instruction output to co-processor decode*/
 	cp_insn_out 	<= (is_cp_insn_w) ? insn_in : 30'b0; 	//if is a co-processor instruction, output instruction to
                   		                                        //co-processor decoder
	/*Memory access signal output*/
	mem_write_out 	<= mem_write_req_w;
	mem_read_out 	<= mem_read_req_w;
	
 	pc_change_rel_out <= pc_rel_w;
	pc_change_abs_out <= pc_abs_w;

	/*Register selection and outputs*/
	if(imm_sel_w == OPC_LI) begin //determine which register bank to use, from DSEL
		reg_select_out	<= { 1'b0, dsel_li_w}; //lower 2 bits determine file, upper two bits determine signed, upper or lower 16 bits
	end else if(sys_insn_w && ( funct_sys_w & (8'h02 ))) begin //if system instruction, need to check if accessing system registers, last two bits matter here
		reg_select_out	<= 5'b10000; //upper most bit is for accessing special purpose registers; maps to memory address to make 8 bit registers easier
	end else begin //everything else should just use general purpose register file
		reg_select_out	<= 5'b0;
	end

	rsa_out <= (use_rsa_w) ? rsa_addr_w : 5'b0;
	rsb_out <= (use_rsb_w) ? rsb_addr_w : 5'b0;
	rd_out  <= (use_rd_w ) ? rd_addr_w  : 5'b0;

	insn_pc_out <= insn_pc_in; //may need to alter this value, but unsure so leave it

	/*** Selecting immediate values ***/
	if(!is_cp_insn_w) begin
		case (imm_sel_w) //figure out what immediate value to use
			OPC_IMM:		imm_out <= {9'b0 ,imm_i_w};
			OPC_LD:			imm_out <= {7'b0, imm_ld_w};
			OPC_ST:			imm_out <= {7'b0, imm_st_w};
			OPC_LI:			imm_out <= {6'b0, imm_li_w};
			OPC_JMP:		imm_out <= imm_j_w;
			OPC_JLNK:		imm_out <= imm_j_w;
			OPC_BRANCH:		imm_out <= {7'b0, imm_b_w};
			default:		imm_out <= 21'b0;	//this may be redundant or cause errors, not sure yet
		endcase
		/*co processor instruction immediates; right now just system insn due to direct
		* affects on main core pipeline */
	end else if(opcode_w[5] & opcode_w[4] & ~(opcode_w[3] | opcode_w[2] | opcode_w[1] | opcode_w[0] ) )begin 
		/*just system instructions*/	
		imm_out <= imm_sys_w;
	end else begin
		imm_out <= 21'b0; //no immediate, default to 0's
	end


	/*System decoding*/
	if( sys_insn_w) begin //if actually a system instruction
		case (funct_sys_w)
			8'h00: begin				//system call
				syscall_out 	<= 1'b1;
				memsync_out		<= 1'b0; 
				pem_inc_req_out	<= 1'b0;
				pem_dec_req_out	<= 1'b0;
			end
		//	8'h01: begin				//system return
		//	end
			8'h04: begin				//memory sync
				syscall_out 	<= 1'b0;
				memsync_out		<= 1'b1;
				pem_inc_req_out	<= 1'b0;
				pem_dec_req_out	<= 1'b0;
				stall_out		<= 1'b1;

			end
			default: begin
				syscall_out 	<= 1'b0;
				memsync_out		<= 1'b0;
				pem_inc_req_out	<= 1'b0;
				pem_dec_req_out	<= 1'b0;
			end
		endcase
	end

	/* Ensure stall_out from memory sync doesn't make the pipeline get stuck */
	if(memsync_w) begin
		if(memstall_count > PIPELINE_LENGTH) begin
			memstall_count 	<= 0;
			memsync_out		<= 1'b0;
		end
		else begin
			memstall_count = memstall_count + 1;
		end
	end


end

endmodule

Fusion-Core-Base/tb/decode_test.v
/* Decode Unit Testbench*/
`timescale 1ns / 100ps
`include "../decode_32.v"

module decode_test();

localparam	MEM_SIZE =	91;


/* Clocks */
reg clk;
always
	#10 clk = ~ clk; //100MHz

/* Input signals to drive */
reg			reset;
reg			stall;
reg	[31:0]	insn;	
reg	[31:0]	insn_address;
//integer		insn_address;
reg	[7:0]	sysreg_data_input;

/* Output signals to observe*/
wire 	[4:0]	reg_select;
wire	[4:0]	rsa;
wire	[4:0]	rsb;
wire	[4:0]	rd;
wire	[20:0]	imm;
wire	[3:0]	aluop;
wire			jlnk;
wire			pc_change_relative;
wire			pc_change_absolute;
wire			mem_read;
wire			mem_write;
wire			nri_flag;
wire	[1:0]	branch_funct;
wire			stall_output;
wire			memsync;
wire			syscall;
wire			permission_inc;
wire			permission_dec;
wire	[7:0]	sysreg_addr;
wire	[7:0]	sysreg_data;
wire	[31:0]	insn_pc_output;
wire	[30:0]	cp_insn;

/* Memory Test Registers */
reg	[31:0]	insn_mem	[0:MEM_SIZE-1]; //1024 addresses, 2^10

decode_32 decode_ut(		//Decode unit under test
	.insn_in(insn),				//Instruction Input
	.reset_in(reset),			//Reset line input (active low)
	.clk_in(clk),				//Clock input
	.insn_pc_in(insn_address),			//Current instruction PC Address
	.stall_in(stall),			//CCCP Leader... nah just a stall signal
	.reg_select_out(reg_select),		//What register bank the instruction wants to access
	.rsa_out(rsa),				//RSa address
	.rsb_out(rsb),				//RSb address
	.rd_out(rd),				//Rd address
	.imm_out(imm),				//Immediate value (if used)
	.aluop_out(aluop),			//What operation to tell the ALU to do
	.jlnk_out(jlnk),			//Saving the PC to $R4/RA?
	.pc_change_rel_out(pc_change_relative),	//PC Relative address change
	.pc_change_abs_out(pc_change_absolute),	//PC Absolute address change
	.mem_read_out(mem_read),		//Memory read access
	.mem_write_out(mem_write),		//Memory write access
	.nri_flg_out(nri_flag),			//Not a real instruction, flag
	.branch_funct_out(branch_funct),	//Branch code, determines if branch should be taken or not along with output
	.stall_out(stall_output),			//Send stall signal out
	.memsync_out(memsync),			//Sync memory signal
	.syscall_out(syscall),			//Instruction is system call
	.pem_inc_req_out(permission_inc),		//Permission increase request
	.pem_dec_req_out(permission_dec),		//Permission decrease request
	.sysreg_addr_out(sysreg_addr),		//System/Special purpose register address to access
	.sysreg_data_out(sysreg_data),		//Data to write to System/Special purpose register
	.sysreg_data_in(sysreg_data_input),		//Data read from System/Special purpose register
	.insn_pc_out(insn_pc_output),			//Output PC value (for debugging)

	/*Co-Processor Connections*/
	.cp_insn_out(cp_insn)			//Output instruction to Co-Processor to decode

	);

integer i;

integer count;
/* Initial Conditions  */
initial begin
	$dumpfile("decode.vcd");
	$dumpvars(0,decode_test);
	$readmemh("test_insn.txt", insn_mem); //Fill memory
	for( i = 0; i < MEM_SIZE; i = i + 1) begin
		$display("Data read from insn_mem: %h | address: %h", insn_mem[i], i);
		#10;

	end
	#100 //wait a bit before doing anything
	clk						<= 1'b0;

	reset 					<= 1'b0;	//put into reset to start
	#10	//let the reset propagate
	stall 					<= 1'b0;		
//	insn					<= 32'b0;
	insn_address 			<= 0;
	sysreg_data_input 		<= 8'b0;
	#10
	reset					<= 1'b1;	//and they're off!
	count					<= 0;
/* Testing */
//always @(posedge clk) begin
	#5
	for( insn_address = 0; insn_address <= MEM_SIZE; insn_address = insn_address + 1) begin
		#20;
		insn	<= insn_mem[insn_address];			//get instruction from memory address
		$display("Current Address: %h | Instruction: %h", insn_address, insn);

	end

//end
	$finish;
end
endmodule

Fusion-Core-Base/tb/decode.vcd
$date
	Sun Feb 25 14:32:41 2018
$end
$version
	Icarus Verilog
$end
$timescale
	100ps
$end
$scope module decode_test $end
$var wire 8 ! sysreg_data [7:0] $end
$var wire 8 " sysreg_addr [7:0] $end
$var wire 1 # syscall $end
$var wire 1 $ stall_output $end
$var wire 5 % rsb [4:0] $end
$var wire 5 & rsa [4:0] $end
$var wire 5 ' reg_select [4:0] $end
$var wire 5 ( rd [4:0] $end
$var wire 1 ) permission_inc $end
$var wire 1 * permission_dec $end
$var wire 1 + pc_change_relative $end
$var wire 1 , pc_change_absolute $end
$var wire 1 - nri_flag $end
$var wire 1 . memsync $end
$var wire 1 / mem_write $end
$var wire 1 0 mem_read $end
$var wire 1 1 jlnk $end
$var wire 32 2 insn_pc_output [31:0] $end
$var wire 21 3 imm [20:0] $end
$var wire 31 4 cp_insn [30:0] $end
$var wire 2 5 branch_funct [1:0] $end
$var wire 4 6 aluop [3:0] $end
$var reg 1 7 clk $end
$var reg 32 8 insn [31:0] $end
$var reg 32 9 insn_address [31:0] $end
$var reg 1 : reset $end
$var reg 1 ; stall $end
$var reg 8 < sysreg_data_input [7:0] $end
$var integer 32 = count [31:0] $end
$var integer 32 > i [31:0] $end
$scope module decode_ut $end
$var wire 1 ? aluop_addsig_w $end
$var wire 1 @ aluop_bsig_w $end
$var wire 1 A aluop_intsig_w $end
$var wire 1 7 clk_in $end
$var wire 32 B insn_in [31:0] $end
$var wire 32 C insn_pc_in [31:0] $end
$var wire 1 D mem_access_w $end
$var wire 1 E mem_read_req_w $end
$var wire 1 F mem_write_req_w $end
$var wire 1 G memsync_w $end
$var wire 1 H pc_abs_w $end
$var wire 1 I pc_change_w $end
$var wire 1 J pc_link_w $end
$var wire 1 K pc_rel_w $end
$var wire 1 : reset_in $end
$var wire 1 ; stall_in $end
$var wire 1 L sys_insn_w $end
$var wire 8 M sysreg_data_in [7:0] $end
$var wire 1 N use_imm_w $end
$var wire 1 O use_rd_w $end
$var wire 1 P use_rsa_w $end
$var wire 1 Q use_rsb_w $end
$var wire 5 R rsb_addr_w [4:0] $end
$var wire 5 S rsa_addr_w [4:0] $end
$var wire 5 T rd_addr_w [4:0] $end
$var wire 6 U opcode_w [5:0] $end
$var wire 1 V is_cp_insn_w $end
$var wire 8 W imm_sys_w [7:0] $end
$var wire 14 X imm_st_w [13:0] $end
$var wire 5 Y imm_sel_w [4:0] $end
$var wire 16 Z imm_li_w [15:0] $end
$var wire 14 [ imm_ld_w [13:0] $end
$var wire 21 \ imm_j_w [20:0] $end
$var wire 12 ] imm_i_w [11:0] $end
$var wire 14 ^ imm_b_w [13:0] $end
$var wire 8 _ funct_sys_w [7:0] $end
$var wire 2 ` funct_st_w [1:0] $end
$var wire 2 a funct_ld_w [1:0] $end
$var wire 2 b funct_b_w [1:0] $end
$var wire 4 c dsel_li_w [3:0] $end
$var wire 4 d aluop_w [3:0] $end
$var reg 4 e aluop_out [3:0] $end
$var reg 2 f branch_funct_out [1:0] $end
$var reg 31 g cp_insn_out [30:0] $end
$var reg 21 h imm_out [20:0] $end
$var reg 32 i insn_pc_out [31:0] $end
$var reg 1 1 jlnk_out $end
$var reg 1 0 mem_read_out $end
$var reg 1 / mem_write_out $end
$var reg 3 j memstall_count [2:0] $end
$var reg 1 . memsync_out $end
$var reg 1 - nri_flg_out $end
$var reg 1 , pc_change_abs_out $end
$var reg 1 + pc_change_rel_out $end
$var reg 1 * pem_dec_req_out $end
$var reg 1 ) pem_inc_req_out $end
$var reg 5 k rd_out [4:0] $end
$var reg 5 l reg_select_out [4:0] $end
$var reg 5 m rsa_out [4:0] $end
$var reg 5 n rsb_out [4:0] $end
$var reg 1 $ stall_out $end
$var reg 1 # syscall_out $end
$var reg 8 o sysreg_addr_out [7:0] $end
$var reg 8 p sysreg_data_out [7:0] $end
$upscope $end
$upscope $end
$enddefinitions $end
#0
$dumpvars
bx p
bx o
bx n
bx m
bx l
bx k
bx j
bx i
bx h
bx g
bx f
bx e
bx d
bx c
bx b
bx a
bx `
bx _
bx ^
bx ]
bx \
bx [
bx Z
bx Y
bx X
bx W
xV
bx U
bx T
bx S
bx R
xQ
xP
xO
xN
bx M
xL
xK
xJ
xI
xH
xG
xF
xE
xD
bx C
bx B
xA
x@
x?
b0 >
bx =
bx <
x;
x:
bx 9
bx 8
x7
bx 6
bx 5
bx 4
bx 3
bx 2
x1
x0
x/
x.
x-
x,
x+
x*
x)
bx (
bx '
bx &
bx %
x$
x#
bx "
bx !
$end
#100
b1 >
#200
b10 >
#300
b11 >
#400
b100 >
#500
b101 >
#600
b110 >
#700
b111 >
#800
b1000 >
#900
b1001 >
#1000
b1010 >
#1100
b1011 >
#1200
b1100 >
#1300
b1101 >
#1400
b1110 >
#1500
b1111 >
#1600
b10000 >
#1700
b10001 >
#1800
b10010 >
#1900
b10011 >
#2000
b10100 >
#2100
b10101 >
#2200
b10110 >
#2300
b10111 >
#2400
b11000 >
#2500
b11001 >
#2600
b11010 >
#2700
b11011 >
#2800
b11100 >
#2900
b11101 >
#3000
b11110 >
#3100
b11111 >
#3200
b100000 >
#3300
b100001 >
#3400
b100010 >
#3500
b100011 >
#3600
b100100 >
#3700
b100101 >
#3800
b100110 >
#3900
b100111 >
#4000
b101000 >
#4100
b101001 >
#4200
b101010 >
#4300
b101011 >
#4400
b101100 >
#4500
b101101 >
#4600
b101110 >
#4700
b101111 >
#4800
b110000 >
#4900
b110001 >
#5000
b110010 >
#5100
b110011 >
#5200
b110100 >
#5300
b110101 >
#5400
b110110 >
#5500
b110111 >
#5600
b111000 >
#5700
b111001 >
#5800
b111010 >
#5900
b111011 >
#6000
b111100 >
#6100
b111101 >
#6200
b111110 >
#6300
b111111 >
#6400
b1000000 >
#6500
b1000001 >
#6600
b1000010 >
#6700
b1000011 >
#6800
b1000100 >
#6900
b1000101 >
#7000
b1000110 >
#7100
b1000111 >
#7200
b1001000 >
#7300
b1001001 >
#7400
b1001010 >
#7500
b1001011 >
#7600
b1001100 >
#7700
b1001101 >
#7800
b1001110 >
#7900
b1001111 >
#8000
b1010000 >
#8100
b1010001 >
#8200
b1010010 >
#8300
b1010011 >
#8400
b1010100 >
#8500
b1010101 >
#8600
b1010110 >
#8700
b1010111 >
#8800
b1011000 >
#8900
b1011001 >
#9000
b1011010 >
#9100
b1011011 >
#10100
0$
b0 4
b0 g
b0 2
b0 i
b0 !
b0 p
b0 "
b0 o
0*
0)
0#
0.
b0 5
b0 f
0-
0/
00
0,
0+
01
b0 (
b0 k
b0 %
b0 n
b0 &
b0 m
b0 3
b0 h
b0 '
b0 l
b0 6
b0 e
0:
07
#10200
b0 2
b0 i
bx (
bx k
bx %
bx n
bx &
bx m
x,
x+
x0
x/
bx 4
bx g
b0 <
b0 M
b0 9
b0 C
0;
b0 5
b0 f
b0 6
b0 e
17
#10300
b0 4
b0 g
0/
00
0,
0+
b0 (
b0 k
b0 %
b0 n
b0 &
b0 m
b0 5
b0 f
b0 6
b0 e
b0 =
1:
07
#10400
bx (
bx k
bx %
bx n
bx &
bx m
x,
x+
x0
x/
bx 4
bx g
bx 5
bx f
b1111 6
b1111 e
17
#10500
07
#10550
1A
0@
0F
0E
0J
1O
0Q
0?
0K
0H
0G
b10110 Y
0I
0D
0L
1P
1N
0V
b0 c
b10110 U
b0 S
b0 R
b11111 T
b0 d
b0 a
b11 `
b0 b
b10 _
b101010 ]
b1010100000 [
b1010100000 Z
b1010100000 X
b111110000001010100000 \
b11111010101000 ^
b10100000 W
b1011011111000000000001010100000 8
b1011011111000000000001010100000 B
b1 9
b1 C
#10600
b101010 3
b101010 h
b1 2
b1 i
b11111 (
b11111 k
b0 %
b0 n
b0 &
b0 m
0,
0+
00
0/
b0 4
b0 g
b0 5
b0 f
b0 6
b0 e
17
#10700
07
#10750
b11110 T
b111100000001010100000 \
b11110010101000 ^
b1011011110000000000001010100000 8
b1011011110000000000001010100000 B
b10 9
b10 C
#10800
b10 2
b10 i
b11110 (
b11110 k
17
#10900
07
#10950
b11101 T
b111010000001010100000 \
b11101010101000 ^
b1011011101000000000001010100000 8
b1011011101000000000001010100000 B
b11 9
b11 C
#11000
b11 2
b11 i
b11101 (
b11101 k
17
#11100
07
#11150
b11100 T
b111000000001010100000 \
b11100010101000 ^
b1011011100000000000001010100000 8
b1011011100000000000001010100000 B
b100 9
b100 C
#11200
b100 2
b100 i
b11100 (
b11100 k
17
#11300
07
#11350
b11011 T
b110110000001010100000 \
b11011010101000 ^
b1011011011000000000001010100000 8
b1011011011000000000001010100000 B
b101 9
b101 C
#11400
b101 2
b101 i
b11011 (
b11011 k
17
#11500
07
#11550
b11010 T
b110100000001010100000 \
b11010010101000 ^
b1011011010000000000001010100000 8
b1011011010000000000001010100000 B
b110 9
b110 C
#11600
b110 2
b110 i
b11010 (
b11010 k
17
#11700
07
#11750
b11001 T
b110010000001010100000 \
b11001010101000 ^
b1011011001000000000001010100000 8
b1011011001000000000001010100000 B
b111 9
b111 C
#11800
b111 2
b111 i
b11001 (
b11001 k
17
#11900
07
#11950
b11000 T
b110000000001010100000 \
b11000010101000 ^
b1011011000000000000001010100000 8
b1011011000000000000001010100000 B
b1000 9
b1000 C
#12000
b1000 2
b1000 i
b11000 (
b11000 k
17
#12100
07
#12150
b10111 T
b10 `
b101110000001010100000 \
b10111010101000 ^
b1011010111000000000001010100000 8
b1011010111000000000001010100000 B
b1001 9
b1001 C
#12200
b1001 2
b1001 i
b10111 (
b10111 k
17
#12300
07
#12350
b10110 T
b101100000001010100000 \
b10110010101000 ^
b1011010110000000000001010100000 8
b1011010110000000000001010100000 B
b1010 9
b1010 C
#12400
b1010 2
b1010 i
b10110 (
b10110 k
17
#12500
07
#12550
b10101 T
b101010000001010100000 \
b10101010101000 ^
b1011010101000000000001010100000 8
b1011010101000000000001010100000 B
b1011 9
b1011 C
#12600
b1011 2
b1011 i
b10101 (
b10101 k
17
#12700
07
#12750
b10100 T
b101000000001010100000 \
b10100010101000 ^
b1011010100000000000001010100000 8
b1011010100000000000001010100000 B
b1100 9
b1100 C
#12800
b1100 2
b1100 i
b10100 (
b10100 k
17
#12900
07
#12950
b10011 T
b100110000001010100000 \
b10011010101000 ^
b1011010011000000000001010100000 8
b1011010011000000000001010100000 B
b1101 9
b1101 C
#13000
b1101 2
b1101 i
b10011 (
b10011 k
17
#13100
07
#13150
b10010 T
b100100000001010100000 \
b10010010101000 ^
b1011010010000000000001010100000 8
b1011010010000000000001010100000 B
b1110 9
b1110 C
#13200
b1110 2
b1110 i
b10010 (
b10010 k
17
#13300
07
#13350
b10001 T
b100010000001010100000 \
b10001010101000 ^
b1011010001000000000001010100000 8
b1011010001000000000001010100000 B
b1111 9
b1111 C
#13400
b1111 2
b1111 i
b10001 (
b10001 k
17
#13500
07
#13550
b10000 T
b100000000001010100000 \
b10000010101000 ^
b1011010000000000000001010100000 8
b1011010000000000000001010100000 B
b10000 9
b10000 C
#13600
b10000 2
b10000 i
b10000 (
b10000 k
17
#13700
07
#13750
b1111 T
b1 `
b11110000001010100000 \
b1111010101000 ^
b1011001111000000000001010100000 8
b1011001111000000000001010100000 B
b10001 9
b10001 C
#13800
b10001 2
b10001 i
b1111 (
b1111 k
17
#13900
07
#13950
b1110 T
b11100000001010100000 \
b1110010101000 ^
b1011001110000000000001010100000 8
b1011001110000000000001010100000 B
b10010 9
b10010 C
#14000
b10010 2
b10010 i
b1110 (
b1110 k
17
#14100
07
#14150
b1101 T
b11010000001010100000 \
b1101010101000 ^
b1011001101000000000001010100000 8
b1011001101000000000001010100000 B
b10011 9
b10011 C
#14200
b10011 2
b10011 i
b1101 (
b1101 k
17
#14300
07
#14350
b1100 T
b11000000001010100000 \
b1100010101000 ^
b1011001100000000000001010100000 8
b1011001100000000000001010100000 B
b10100 9
b10100 C
#14400
b10100 2
b10100 i
b1100 (
b1100 k
17
#14500
07
#14550
b1011 T
b10110000001010100000 \
b1011010101000 ^
b1011001011000000000001010100000 8
b1011001011000000000001010100000 B
b10101 9
b10101 C
#14600
b10101 2
b10101 i
b1011 (
b1011 k
17
#14700
07
#14750
b1010 T
b10100000001010100000 \
b1010010101000 ^
b1011001010000000000001010100000 8
b1011001010000000000001010100000 B
b10110 9
b10110 C
#14800
b10110 2
b10110 i
b1010 (
b1010 k
17
#14900
07
#14950
b1001 T
b10010000001010100000 \
b1001010101000 ^
b1011001001000000000001010100000 8
b1011001001000000000001010100000 B
b10111 9
b10111 C
#15000
b10111 2
b10111 i
b1001 (
b1001 k
17
#15100
07
#15150
b1000 T
b10000000001010100000 \
b1000010101000 ^
b1011001000000000000001010100000 8
b1011001000000000000001010100000 B
b11000 9
b11000 C
#15200
b11000 2
b11000 i
b1000 (
b1000 k
17
#15300
07
#15350
b111 T
b0 `
b1110000001010100000 \
b111010101000 ^
b1011000111000000000001010100000 8
b1011000111000000000001010100000 B
b11001 9
b11001 C
#15400
b11001 2
b11001 i
b111 (
b111 k
17
#15500
07
#15550
b110 T
b1100000001010100000 \
b110010101000 ^
b1011000110000000000001010100000 8
b1011000110000000000001010100000 B
b11010 9
b11010 C
#15600
b11010 2
b11010 i
b110 (
b110 k
17
#15700
07
#15750
b101 T
b1010000001010100000 \
b101010101000 ^
b1011000101000000000001010100000 8
b1011000101000000000001010100000 B
b11011 9
b11011 C
#15800
b11011 2
b11011 i
b101 (
b101 k
17
#15900
07
#15950
b100 T
b1000000001010100000 \
b100010101000 ^
b1011000100000000000001010100000 8
b1011000100000000000001010100000 B
b11100 9
b11100 C
#16000
b11100 2
b11100 i
b100 (
b100 k
17
#16100
07
#16150
b11 T
b110000001010100000 \
b11010101000 ^
b1011000011000000000001010100000 8
b1011000011000000000001010100000 B
b11101 9
b11101 C
#16200
b11101 2
b11101 i
b11 (
b11 k
17
#16300
07
#16350
b10 T
b100000001010100000 \
b10010101000 ^
b1011000010000000000001010100000 8
b1011000010000000000001010100000 B
b11110 9
b11110 C
#16400
b11110 2
b11110 i
b10 (
b10 k
17
#16500
07
#16550
b1 T
b10000001010100000 \
b1010101000 ^
b1011000001000000000001010100000 8
b1011000001000000000001010100000 B
b11111 9
b11111 C
#16600
b11111 2
b11111 i
b1 (
b1 k
17
#16700
07
#16750
b0 T
b1010100000 \
b10101000 ^
b1011000000000000000001010100000 8
b1011000000000000000001010100000 B
b100000 9
b100000 C
#16800
b100000 2
b100000 i
b0 (
b0 k
17
#16900
07
